radge/__init__.py
radge/graph.py
radge/numbers.py
radge/polygon.py
radge/sequences.py
radge/string.py
radge/utils.py
radge-1.3.0.dist-info/METADATA
radge-1.3.0.dist-info/WHEEL
radge-1.3.0.dist-info/licenses/LICENSE
radge-1.3.0.dist-info/RECORD
