Metadata-Version: 2.3
Name: radge
Version: 1.3.0
Summary: A random algorithmic data generator
Author-email: Antoni Zasada <zsd.antoni@gmail.com>
License-File: LICENSE
Requires-Python: >=3.8
